<?xml version="1.0" encoding="UTF-8"?>
<!DOCTYPE why3session PUBLIC "-//Why3//proof session v5//EN"
"http://why3.lri.fr/why3session.dtd">
<why3session shape_version="6">
<prover id="0" name="CVC5" version="0.0.7-gnatprove" timelimit="0" steplimit="24616" memlimit="0"/>
<prover id="1" name="Trivial" version="1.0" alternative="trivial" timelimit="1" steplimit="1" memlimit="1000"/>
<file format="gnat-json" proved="true">
<path name=".."/><path name=".."/><path name=".."/><path name="objs"/>
<path name="release"/><path name="gnatprove"/><path name="48dc802103f49b397b87-ildren__prove_taskoptionid_in_map.gnat-json"/>
<theory name="Assignment_tree_branch_bound__children__prove_taskoptionid_in_map__subprogram_def" proved="true">
 <goal name="def&#39;vc" proved="true">
 <transf name="split_goal_wp_conj" proved="true" >
  <goal name="def&#39;vc.0" proved="true">
  <proof prover="0" steplimit="8501"><result status="valid" steps="7728"/></proof>
  </goal>
  <goal name="def&#39;vc.1" proved="true">
  <proof prover="1"><result status="valid" steps="1"/></proof>
  </goal>
  <goal name="def&#39;vc.2" proved="true">
  <proof prover="0" steplimit="8960"><result status="valid" steps="8145"/></proof>
  </goal>
  <goal name="def&#39;vc.3" proved="true">
  <proof prover="1"><result status="valid" steps="1"/></proof>
  </goal>
  <goal name="def&#39;vc.4" proved="true">
  <proof prover="1"><result status="valid" steps="1"/></proof>
  </goal>
  <goal name="def&#39;vc.5" proved="true">
  <proof prover="0" steplimit="13309"><result status="valid" steps="12099"/></proof>
  </goal>
  <goal name="def&#39;vc.6" proved="true">
  <proof prover="0" steplimit="13452"><result status="valid" steps="12229"/></proof>
  </goal>
  <goal name="def&#39;vc.7" proved="true">
  <proof prover="0" steplimit="13454"><result status="valid" steps="12230"/></proof>
  </goal>
  <goal name="def&#39;vc.8" proved="true">
  <proof prover="1"><result status="valid" steps="1"/></proof>
  </goal>
  <goal name="def&#39;vc.9" proved="true">
  <proof prover="0" steplimit="24719"><result status="valid" steps="22471"/></proof>
  </goal>
  <goal name="def&#39;vc.10" proved="true">
  <proof prover="0" steplimit="13489"><result status="valid" steps="12262"/></proof>
  </goal>
  <goal name="def&#39;vc.11" proved="true">
  <proof prover="0" steplimit="13490"><result status="valid" steps="12263"/></proof>
  </goal>
  <goal name="def&#39;vc.12" proved="true">
  <proof prover="0"><result status="valid" steps="22378"/></proof>
  </goal>
  <goal name="def&#39;vc.13" proved="true">
  <proof prover="0"><result status="valid" steps="22378"/></proof>
  </goal>
  <goal name="def&#39;vc.14" proved="true">
  <proof prover="1"><result status="valid" steps="1"/></proof>
  </goal>
  <goal name="def&#39;vc.15" proved="true">
  <proof prover="0" steplimit="27297"><result status="valid" steps="24815"/></proof>
  </goal>
  <goal name="def&#39;vc.16" proved="true">
  <proof prover="0" steplimit="24738"><result status="valid" steps="22489"/></proof>
  </goal>
  <goal name="def&#39;vc.17" proved="true">
  <proof prover="0" steplimit="24736"><result status="valid" steps="22487"/></proof>
  </goal>
  <goal name="def&#39;vc.18" proved="true">
  <proof prover="1"><result status="valid" steps="1"/></proof>
  </goal>
  <goal name="def&#39;vc.19" proved="true">
  <proof prover="0" steplimit="28073"><result status="valid" steps="25520"/></proof>
  </goal>
  <goal name="def&#39;vc.20" proved="true">
  <proof prover="0" steplimit="13535"><result status="valid" steps="12304"/></proof>
  </goal>
  <goal name="def&#39;vc.21" proved="true">
  <proof prover="0" steplimit="13533"><result status="valid" steps="12302"/></proof>
  </goal>
  <goal name="def&#39;vc.22" proved="true">
  <proof prover="0" steplimit="13544"><result status="valid" steps="12312"/></proof>
  </goal>
  <goal name="def&#39;vc.23" proved="true">
  <proof prover="0" steplimit="13537"><result status="valid" steps="12306"/></proof>
  </goal>
  <goal name="def&#39;vc.24" proved="true">
  <proof prover="0" steplimit="13522"><result status="valid" steps="12292"/></proof>
  </goal>
  <goal name="def&#39;vc.25" proved="true">
  <proof prover="0" steplimit="13525"><result status="valid" steps="12295"/></proof>
  </goal>
  <goal name="def&#39;vc.26" proved="true">
  <proof prover="0" steplimit="13586"><result status="valid" steps="12350"/></proof>
  </goal>
  <goal name="def&#39;vc.27" proved="true">
  <proof prover="1"><result status="valid" steps="1"/></proof>
  </goal>
  <goal name="def&#39;vc.28" proved="true">
  <proof prover="1"><result status="valid" steps="1"/></proof>
  </goal>
  <goal name="def&#39;vc.29" proved="true">
  <proof prover="0" steplimit="13835"><result status="valid" steps="12577"/></proof>
  </goal>
  <goal name="def&#39;vc.30" proved="true">
  <proof prover="0" steplimit="13833"><result status="valid" steps="12575"/></proof>
  </goal>
  <goal name="def&#39;vc.31" proved="true">
  <proof prover="0" steplimit="14038"><result status="valid" steps="12761"/></proof>
  </goal>
  <goal name="def&#39;vc.32" proved="true">
  <proof prover="0" steplimit="14035"><result status="valid" steps="12759"/></proof>
  </goal>
  <goal name="def&#39;vc.33" proved="true">
  <proof prover="0" steplimit="17695"><result status="valid" steps="16086"/></proof>
  </goal>
  <goal name="def&#39;vc.34" proved="true">
  <proof prover="0" steplimit="17943"><result status="valid" steps="16311"/></proof>
  </goal>
  <goal name="def&#39;vc.35" proved="true">
  <proof prover="0" steplimit="26716"><result status="valid" steps="24287"/></proof>
  </goal>
  <goal name="def&#39;vc.36" proved="true">
  <proof prover="1"><result status="valid" steps="1"/></proof>
  </goal>
  <goal name="def&#39;vc.37" proved="true">
  <proof prover="1"><result status="valid" steps="1"/></proof>
  </goal>
  <goal name="def&#39;vc.38" proved="true">
  <proof prover="1"><result status="valid" steps="1"/></proof>
  </goal>
  <goal name="def&#39;vc.39" proved="true">
  <proof prover="0" steplimit="13531"><result status="valid" steps="12300"/></proof>
  </goal>
  <goal name="def&#39;vc.40" proved="true">
  <proof prover="0" steplimit="26006"><result status="valid" steps="23641"/></proof>
  </goal>
  <goal name="def&#39;vc.41" proved="true">
  <proof prover="0" steplimit="14161"><result status="valid" steps="12873"/></proof>
  </goal>
  <goal name="def&#39;vc.42" proved="true">
  <proof prover="0" steplimit="14159"><result status="valid" steps="12871"/></proof>
  </goal>
  <goal name="def&#39;vc.43" proved="true">
  <proof prover="0" steplimit="14361"><result status="valid" steps="13055"/></proof>
  </goal>
  <goal name="def&#39;vc.44" proved="true">
  <proof prover="0" steplimit="14359"><result status="valid" steps="13053"/></proof>
  </goal>
  <goal name="def&#39;vc.45" proved="true">
  <proof prover="0" steplimit="18103"><result status="valid" steps="16457"/></proof>
  </goal>
  <goal name="def&#39;vc.46" proved="true">
  <proof prover="0" steplimit="18429"><result status="valid" steps="16753"/></proof>
  </goal>
  <goal name="def&#39;vc.47" proved="true">
  <proof prover="0" steplimit="28135"><result status="valid" steps="25577"/></proof>
  </goal>
  <goal name="def&#39;vc.48" proved="true">
  <proof prover="1"><result status="valid" steps="1"/></proof>
  </goal>
  <goal name="def&#39;vc.49" proved="true">
  <proof prover="0" steplimit="14752"><result status="valid" steps="13410"/></proof>
  </goal>
  <goal name="def&#39;vc.50" proved="true">
  <proof prover="0" steplimit="14749"><result status="valid" steps="13408"/></proof>
  </goal>
  <goal name="def&#39;vc.51" proved="true">
  <proof prover="0" steplimit="14978"><result status="valid" steps="13616"/></proof>
  </goal>
  <goal name="def&#39;vc.52" proved="true">
  <proof prover="0" steplimit="14976"><result status="valid" steps="13614"/></proof>
  </goal>
  <goal name="def&#39;vc.53" proved="true">
  <proof prover="0" steplimit="14092"><result status="valid" steps="12810"/></proof>
  </goal>
  <goal name="def&#39;vc.54" proved="true">
  <proof prover="0" steplimit="14083"><result status="valid" steps="12802"/></proof>
  </goal>
  <goal name="def&#39;vc.55" proved="true">
  <proof prover="0" steplimit="28847"><result status="valid" steps="26224"/></proof>
  </goal>
  <goal name="def&#39;vc.56" proved="true">
  <proof prover="0" steplimit="19279"><result status="valid" steps="17526"/></proof>
  </goal>
  <goal name="def&#39;vc.57" proved="true">
  <proof prover="0" steplimit="19444"><result status="valid" steps="17676"/></proof>
  </goal>
  <goal name="def&#39;vc.58" proved="true">
  <proof prover="0" steplimit="19277"><result status="valid" steps="17524"/></proof>
  </goal>
  <goal name="def&#39;vc.59" proved="true">
  <proof prover="0" steplimit="42880"><result status="valid" steps="38981"/></proof>
  </goal>
  <goal name="def&#39;vc.60" proved="true">
  <proof prover="0" steplimit="42905"><result status="valid" steps="39004"/></proof>
  </goal>
  <goal name="def&#39;vc.61" proved="true">
  <proof prover="0" steplimit="43304"><result status="valid" steps="39367"/></proof>
  </goal>
  <goal name="def&#39;vc.62" proved="true">
  <proof prover="0" steplimit="57685"><result status="valid" steps="52440"/></proof>
  </goal>
  <goal name="def&#39;vc.63" proved="true">
  <proof prover="0" steplimit="19277"><result status="valid" steps="17524"/></proof>
  </goal>
  <goal name="def&#39;vc.64" proved="true">
  <proof prover="0" steplimit="14989"><result status="valid" steps="13626"/></proof>
  </goal>
  <goal name="def&#39;vc.65" proved="true">
  <proof prover="0" steplimit="14987"><result status="valid" steps="13624"/></proof>
  </goal>
  <goal name="def&#39;vc.66" proved="true">
  <proof prover="0" steplimit="18753"><result status="valid" steps="17048"/></proof>
  </goal>
  <goal name="def&#39;vc.67" proved="true">
  <proof prover="0" steplimit="19559"><result status="valid" steps="17780"/></proof>
  </goal>
  <goal name="def&#39;vc.68" proved="true">
  <proof prover="0" steplimit="35221"><result status="valid" steps="32019"/></proof>
  </goal>
  <goal name="def&#39;vc.69" proved="true">
  <proof prover="1"><result status="valid" steps="1"/></proof>
  </goal>
  <goal name="def&#39;vc.70" proved="true">
  <proof prover="1"><result status="valid" steps="1"/></proof>
  </goal>
  <goal name="def&#39;vc.71" proved="true">
  <proof prover="0" steplimit="14845"><result status="valid" steps="13495"/></proof>
  </goal>
  <goal name="def&#39;vc.72" proved="true">
  <proof prover="0" steplimit="14843"><result status="valid" steps="13493"/></proof>
  </goal>
  <goal name="def&#39;vc.73" proved="true">
  <proof prover="0" steplimit="15045"><result status="valid" steps="13677"/></proof>
  </goal>
  <goal name="def&#39;vc.74" proved="true">
  <proof prover="0" steplimit="15043"><result status="valid" steps="13675"/></proof>
  </goal>
  <goal name="def&#39;vc.75" proved="true">
  <proof prover="0" steplimit="19640"><result status="valid" steps="17854"/></proof>
  </goal>
  <goal name="def&#39;vc.76" proved="true">
  <proof prover="0" steplimit="19625"><result status="valid" steps="17840"/></proof>
  </goal>
  <goal name="def&#39;vc.77" proved="true">
  <proof prover="0" steplimit="35312"><result status="valid" steps="32101"/></proof>
  </goal>
  <goal name="def&#39;vc.78" proved="true">
  <proof prover="1"><result status="valid" steps="1"/></proof>
  </goal>
  <goal name="def&#39;vc.79" proved="true">
  <proof prover="1"><result status="valid" steps="1"/></proof>
  </goal>
  <goal name="def&#39;vc.80" proved="true">
  <proof prover="1"><result status="valid" steps="1"/></proof>
  </goal>
  <goal name="def&#39;vc.81" proved="true">
  <proof prover="0" steplimit="31380"><result status="valid" steps="28527"/></proof>
  </goal>
  <goal name="def&#39;vc.82" proved="true">
  <proof prover="0" steplimit="30185"><result status="valid" steps="27440"/></proof>
  </goal>
  <goal name="def&#39;vc.83" proved="true">
  <proof prover="0" steplimit="25297"><result status="valid" steps="22997"/></proof>
  </goal>
  <goal name="def&#39;vc.84" proved="true">
  <proof prover="0" steplimit="15091"><result status="valid" steps="13719"/></proof>
  </goal>
  <goal name="def&#39;vc.85" proved="true">
  <proof prover="0" steplimit="15091"><result status="valid" steps="13719"/></proof>
  </goal>
  <goal name="def&#39;vc.86" proved="true">
  <proof prover="1"><result status="valid" steps="1"/></proof>
  </goal>
  <goal name="def&#39;vc.87" proved="true">
  <proof prover="0" steplimit="39334"><result status="valid" steps="35758"/></proof>
  </goal>
  <goal name="def&#39;vc.88" proved="true">
  <proof prover="0" steplimit="39355"><result status="valid" steps="35777"/></proof>
  </goal>
  <goal name="def&#39;vc.89" proved="true">
  <proof prover="0" steplimit="105198"><result status="valid" steps="95634"/></proof>
  </goal>
 </transf>
 </goal>
</theory>
</file>
</why3session>
